LICENSE
MANIFEST.in
README.md
setup.cfg
setup.py
requirements/requirements-lint.txt
requirements/requirements-test.txt
requirements/requirements.txt
src/os_aiohttp_utils/VERSION
src/os_aiohttp_utils/__init__.py
src/os_aiohttp_utils/http.py
src/os_aiohttp_utils.egg-info/PKG-INFO
src/os_aiohttp_utils.egg-info/SOURCES.txt
src/os_aiohttp_utils.egg-info/dependency_links.txt
src/os_aiohttp_utils.egg-info/not-zip-safe
src/os_aiohttp_utils.egg-info/requires.txt
src/os_aiohttp_utils.egg-info/top_level.txt
tests/test_version.py